Agent/__init__.py
Agent/ActionsLayer/Agent_player.py
Agent/ActionsLayer/__init__.py
Agent/An/Agent_player.py
Agent/An/__init__.py
Agent/BasicModeling/Agent_player.py
Agent/BasicModeling/__init__.py
Agent/BiasAlgorithm/Agent_player.py
Agent/BiasAlgorithm/__init__.py
Agent/Chain3/Agent_player.py
Agent/Chain3/__init__.py
Agent/Chain4/Agent_player.py
Agent/Chain4/__init__.py
Agent/Ifelse/__init__.py
Agent/KhanhNhat/Agent_player.py
Agent/KhanhNhat/__init__.py
Agent/MultiDimensionAlgorithm/Agent_player.py
Agent/MultiDimensionAlgorithm/__init__.py
Agent/StateBasedAlgorithm/Agent_player.py
Agent/StateBasedAlgorithm/__init__.py
Agent/StateLayer/Agent_player.py
Agent/StateLayer/__init__.py
Agent/TimeBasedAlgorithm/Agent_player.py
Agent/TimeBasedAlgorithm/__init__.py
Agent/Y_random/Agent_player.py
Agent/Y_random/__init__.py
Base/__init__.py
Base/Catan/__init__.py
Base/Catan/_render_func.py
Base/Catan/env.py
Base/CatanNoExchange/__init__.py
Base/CatanNoExchange/_render_func.py
Base/CatanNoExchange/env.py
Base/CatanNoExchange/docs/__init__.py
Base/CatanNoExchange/images/__init__.py
Base/Century/__init__.py
Base/Century/_render_func.py
Base/Century/env.py
Base/Durak/__init__.py
Base/Durak/_render_func.py
Base/Durak/env.py
Base/Exploding_Kitten/__init__.py
Base/Exploding_Kitten/_render_func.py
Base/Exploding_Kitten/env.py
Base/GoFish/__init__.py
Base/GoFish/_render_func.py
Base/GoFish/env.py
Base/Imploding_Kitten/__init__.py
Base/Imploding_Kitten/_render_func.py
Base/Imploding_Kitten/env.py
Base/MachiKoro/__init__.py
Base/MachiKoro/_render_func.py
Base/MachiKoro/env.py
Base/Poker/__init__.py
Base/Poker/_render_func.py
Base/Poker/env.py
Base/Sheriff/__init__.py
Base/Sheriff/_render_func.py
Base/Sheriff/env.py
Base/Sheriff/images/__init__.py
Base/Splendor/__init__.py
Base/Splendor/_render_func.py
Base/Splendor/env.py
Base/Splendor/images/__init__.py
Base/Splendor_v2/__init__.py
Base/Splendor_v2/_render_func.py
Base/Splendor_v2/env.py
Base/Splendor_v3/__init__.py
vis_lab-1.0.5.dist-info/LICENCE.txt
vis_lab-1.0.5.dist-info/METADATA
vis_lab-1.0.5.dist-info/WHEEL
vis_lab-1.0.5.dist-info/top_level.txt
vis_lab-1.0.5.dist-info/RECORD
